pysme/__init__.py
pysme/_version.py
pysme/abund.py
pysme/broadening.py
pysme/config.py
pysme/continuum_and_radial_velocity.py
pysme/cwrapper.py
pysme/data_structure.py
pysme/datafiles_atmospheres.json
pysme/datafiles_nlte.json
pysme/echelle.py
pysme/iliffe_vector.py
pysme/large_file_storage.py
pysme/nlte.py
pysme/persistence.py
pysme/sme.py
pysme/sme_synth.py
pysme/solve.py
pysme/synthesize.py
pysme/uncertainties.py
pysme/util.py
pysme/atmosphere/__init__.py
pysme/atmosphere/atmosphere.py
pysme/atmosphere/interpolation.py
pysme/atmosphere/krzfile.py
pysme/atmosphere/savfile.py
pysme/gui/__init__.py
pysme/gui/plot_colors.py
pysme/gui/plot_plotly.py
pysme/gui/plot_pyplot.py
pysme/linelist/VALD3_ref.bib
pysme/linelist/__init__.py
pysme/linelist/linelist.py
pysme/linelist/vald.py
pysme_astro-5.74.9.dist-info/LICENSE
pysme_astro-5.74.9.dist-info/METADATA
pysme_astro-5.74.9.dist-info/WHEEL
pysme_astro-5.74.9.dist-info/top_level.txt
pysme_astro-5.74.9.dist-info/RECORD
