Metadata-Version: 2.1
Name: pysme-astro
Version: 5.74.9
Summary: Spectroscopy Made Easy
Home-page: https://github.com/AWehrhahn/SME/
Author: Ansgar Wehrhahn, Jeff A. Valenti
Author-email: ansgar.wehrhahn@physics.uu.se, valenti@stsci.edu
License: UNKNOWN
Project-URL: Bug Tracker, https://github.com/AWehrhahn/SME/issues
Project-URL: Documentation, https://pysme-astro.readthedocs.io/en/latest/
Project-URL: Source Code, https://github.com/AWehrhahn/SME/
Platform: UNKNOWN
Classifier: Programming Language :: Python :: 3
Classifier: License :: OSI Approved :: BSD License
Classifier: Operating System :: POSIX :: Linux
Classifier: Operating System :: MacOS :: MacOS X
Classifier: Operating System :: Microsoft :: Windows
Requires-Python: >=3.6
Requires-Dist: numpy
Requires-Dist: scipy
Requires-Dist: astropy
Requires-Dist: pandas
Requires-Dist: wget
Requires-Dist: requests
Requires-Dist: tqdm
Requires-Dist: colorlog
Requires-Dist: emcee
Requires-Dist: pybtex
Requires-Dist: flex-format
